{
	"cards": [
		{
			"id": 1,
			"name": "sint",
			"date": "11",
			"city": "Port Izabella",
			"genre": "ducimus",
			"image": "http://lorempixel.com/640/480?random=1598264061452"
		},
		{
			"id": 2,
			"name": "voluptatem",
			"date": "11",
			"city": "Isacfort",
			"genre": "voluptatibus",
			"image": "http://lorempixel.com/640/480?random=1598264061452"
		},
		{
			"id": 3,
			"name": "aliquid",
			"date": "11",
			"city": "North Florenciohaven",
			"genre": "ut",
			"image": "http://lorempixel.com/640/480?random=1598264061452"
		},
		{
			"id": 4,
			"name": "sit",
			"date": "11",
			"city": "New Jasmin",
			"genre": "quo",
			"image": "http://lorempixel.com/640/480?random=1598264061452"
		},
		{
			"id": 5,
			"name": "optio",
			"date": "11",
			"city": "Hirtheborough",
			"genre": "reprehenderit",
			"image": "http://lorempixel.com/640/480?random=1598264061452"
		},
		{
			"id": 6,
			"name": "sapiente",
			"date": "11",
			"city": "South Schuylermouth",
			"genre": "facere",
			"image": "http://lorempixel.com/640/480?random=1598264061452"
		},
		{
			"id": 7,
			"name": "est",
			"date": "11",
			"city": "Hillltown",
			"genre": "necessitatibus",
			"image": "http://lorempixel.com/640/480?random=1598264061452"
		},
		{
			"id": 8,
			"name": "voluptatum",
			"date": "11",
			"city": "Cartertown",
			"genre": "deleniti",
			"image": "http://lorempixel.com/640/480?random=1598264061452"
		},
		{
			"id": 9,
			"name": "qui",
			"date": "11",
			"city": "Zboncakville",
			"genre": "suscipit",
			"image": "http://lorempixel.com/640/480?random=1598264061453"
		},
		{
			"id": 10,
			"name": "dignissimos",
			"date": "11",
			"city": "Laurenview",
			"genre": "aperiam",
			"image": "http://lorempixel.com/640/480?random=1598264061453"
		},
		{
			"id": 11,
			"name": "dolorum",
			"date": "11",
			"city": "New Juliet",
			"genre": "et",
			"image": "http://lorempixel.com/640/480?random=1598264061453"
		},
		{
			"id": 12,
			"name": "corrupti",
			"date": "11",
			"city": "South Ali",
			"genre": "sit",
			"image": "http://lorempixel.com/640/480?random=1598264061453"
		},
		{
			"id": 13,
			"name": "dignissimos",
			"date": "11",
			"city": "North Hiltonton",
			"genre": "possimus",
			"image": "http://lorempixel.com/640/480?random=1598264061454"
		},
		{
			"id": 14,
			"name": "et",
			"date": "11",
			"city": "Pagacbury",
			"genre": "ab",
			"image": "http://lorempixel.com/640/480?random=1598264061454"
		}
	]
}